{
  "owns": [
    {
      "type": "own",
      "capitalShares": 71.25,
      "held": {
        "name": "Radio Bielefeld Betriebsgesellschaft mbH & Co. KG",
        "squuid": "5be1a6b6-4a8f-4158-a3d4-22aad2f1e1b3"
      },
      "squuid": "5be1a6b7-4685-4b76-a033-f3d755e9818f",
      "state": "active"
    },
    {
      "type": "own",
      "capitalShares": 27.04,
      "held": {
        "name": "Radio Gütersloh Betriebsgesellschaft mbH & Co. KG",
        "squuid": "5be1a6b6-8678-4c3a-80a8-a1e585c9889a"
      },
      "squuid": "5be1a6b7-2548-4ea9-9d9c-76fd7defd882",
      "state": "active"
    },
    {
      "type": "own",
      "capitalShares": 75.0,
      "held": {
        "name": "Radio Herford Betriebsgesellschaft mbH & Co. KG",
        "squuid": "5be1a6b6-d921-4cea-99f5-626673062b59"
      },
      "squuid": "5be1a6b7-3441-4e4e-b32f-6bc189fec4a0",
      "state": "active"
    },
    {
      "type": "own",
      "capitalShares": 75.0,
      "held": {
        "name": "Radio Paderborn Betriebsgesellschaft mbH & Co. KG",
        "squuid": "5be1a6b6-8c11-4c72-82bc-07208f7d0f32"
      },
      "squuid": "5be1a6b7-275c-4957-a5c0-641eaddd75a3",
      "state": "active"
    },
    {
      "type": "own",
      "capitalShares": 3.8,
      "held": {
        "name": "Pressefunk Nordrhein-Westfalen GmbH & Co. KG",
        "squuid": "5be1a6b6-8c11-4526-af08-275ec93dea8b"
      },
      "squuid": "5be1a6b7-ecf2-4ab7-8129-27b8ab3e8548",
      "state": "active"
    },
    {
      "type": "own",
      "capitalShares": 4.8,
      "held": {
        "name": "Lippischer Rundfunk GmbH & Co. KG",
        "squuid": "5be1a6b6-4b3f-4f25-8ecd-85ec1650f50b"
      },
      "squuid": "5be1a6b8-e779-4d44-bf8f-abaef030e27f",
      "state": "active"
    },
    {
      "type": "own",
      "capitalShares": 27.0,
      "held": {
        "name": "Radio Minden-Lübbecke GmbH & Co. KG",
        "squuid": "5be1a6b6-1d3f-41b8-adb3-87fcb17f51e2"
      },
      "squuid": "5be1a6b8-9299-4372-a45e-b610ad26de76",
      "state": "active"
    },
    {
      "type": "own",
      "capitalShares": 68.0,
      "held": {
        "name": "Redaktionsgemeinschaft der ostwestfälisch-lippischen Verlage GmbH & Co. KG",
        "squuid": "5de7ab4e-e35a-4fc7-8289-dd27e04bb28b"
      },
      "squuid": "5de7b429-4a82-4988-9bbe-e89917d2b075",
      "state": "active"
    },
    {
      "type": "own",
      "capitalShares": 50.53,
      "held": {
        "name": "AUDIO MEDIA SERVICE Produktionsgesellschaft mbH & Co. KG",
        "squuid": "5eeb7b89-1d1d-486f-b21f-09fd3bc32248"
      },
      "squuid": "5eeb7e1c-83cd-4c36-bb61-e079c5187793",
      "state": "active"
    },
    {
      "type": "own",
      "capitalShares": 100.0,
      "held": {
        "name": "Haller Kreisblatt Verlags-GmbH",
        "squuid": "5be1a6b6-74c0-4578-9c26-b2c91711672a"
      },
      "squuid": "6082c3ff-b667-40b6-89a3-f35dd8585b40",
      "state": "active"
    },
    {
      "type": "own",
      "capitalShares": 68.0,
      "held": {
        "name": "OWL-Digital GmbH & Co. KG",
        "squuid": "6086b017-2ec8-4344-a998-4bc0af8d8e9a"
      },
      "squuid": "6086b0ff-feb8-4455-a0a5-1c3a5ec84c56",
      "state": "active"
    },
    {
      "type": "own",
      "capitalShares": 0.91,
      "held": {
        "name": "dpa Deutsche Presse Agentur GmbH",
        "squuid": "5be1a6b6-d7c9-45c5-99de-2acb723d2e72"
      },
      "squuid": "61ded1c0-f13f-48ff-80c8-55a5318f7066",
      "state": "active"
    },
    {
      "type": "own",
      "capitalShares": 1.11,
      "held": {
        "name": "Prisma-Verlag GmbH & Co. KG",
        "squuid": "621cc626-22eb-44c9-b383-2237d947b390"
      },
      "squuid": "62274b45-a1d7-4599-9d17-e406ce5d0f1a",
      "state": "active"
    }
  ],
  "state": "active",
  "city": "Bielefeld",
  "pseudoCompany": false,
  "street": "Niedernstr. 21-27",
  "name": "Zeitungsverlag Neue Westfälische GmbH & Co. KG",
  "naturalPerson": false,
  "limitedPartnership": true,
  "squuid": "5be1a6b6-2567-447c-b4a0-60f7702714c2",
  "controlDate": "2023-11-29T16:56:58.502Z",
  "organizations": [
    {
      "squuid": "5adf79c8-9f9e-4b59-a86f-7119603efa99",
      "name": "DL",
      "type": "organization"
    },
    {
      "squuid": "5b0830f6-6588-43fb-93a8-d824a4663969",
      "name": "LFM NRW",
      "type": "organization",
      "fullName": "Landesanstalt für Medien Nordrhein-Westfalen"
    }
  ],
  "zipcode": "33602",
  "operates": [
    {
      "type": "operate",
      "held": {
        "name": "Neue Westfälische",
        "squuid": "5be1a6b1-db08-4c02-8677-a7c7e699c9eb"
      },
      "squuid": "5be1a6b9-aed5-445a-a1a4-f41102d4ab86",
      "state": "active"
    },
    {
      "type": "operate",
      "held": {
        "name": "www.nw.de",
        "squuid": "5be1a6b1-2fbb-43f6-b7d0-779cf9e95d7e"
      },
      "squuid": "5be1a6b9-4043-41b4-b9aa-c2d727f658f7",
      "state": "active"
    },
    {
      "type": "operate",
      "held": {
        "name": "Zeitungsgruppe Neue Westfälische (MVM)",
        "squuid": "5cffa1f5-ae30-43e3-bbe4-3416a3c2d324"
      },
      "squuid": "5cffa2ef-38e9-40b8-9da4-ab8c5a30c660",
      "state": "active"
    },
    {
      "type": "operate",
      "held": {
        "name": "www.fupa.net/region/ostwestfalen",
        "squuid": "6154367f-ae8c-4e97-8eed-9309cca1acd8"
      },
      "squuid": "615436a6-1697-445b-ae8d-326173cb49a7",
      "state": "active"
    },
    {
      "type": "operate",
      "held": {
        "name": "NW am Sonntag",
        "squuid": "64007190-b6b0-4474-a4ca-55af0ea14a70"
      },
      "squuid": "640071c3-0e84-4868-9422-29fd0ab10560",
      "state": "active"
    }
  ],
  "credits": "IJK",
  "ownedBy": [
    {
      "type": "own",
      "capitalShares": 100.0,
      "holder": {
        "name": "Presse-Druck GmbH",
        "squuid": "5be1a6b6-75fa-4176-91ad-ce26bdcbe025"
      },
      "squuid": "5be1a6b7-f2dc-4a5b-8402-f960493f70f3",
      "state": "active"
    },
    {
      "complementaryPartner": true,
      "type": "own",
      "capitalShares": 0.0,
      "holder": {
        "name": "Zeitungsverlag Neue Westfälische Verwaltungsgesellschaft mbH",
        "squuid": "5ecd1f25-edbf-4510-ad3c-fa3c79b29bf8"
      },
      "squuid": "5ecd1f43-5c02-4288-9cfb-3b24d86e1677",
      "state": "active"
    }
  ]
}