{
  "owns": [
    {
      "type": "own",
      "capitalShares": 47.4,
      "held": {
        "name": "Kirchheim & Co GmbH",
        "squuid": "5be1a6b6-1c8f-4212-ba4d-4454c5b14975"
      },
      "squuid": "5be1a6b8-9150-4a5a-85bf-7a8659260a43",
      "state": "active"
    }
  ],
  "state": "active",
  "city": "Frankfurt/M.; Freiburg",
  "pseudoCompany": false,
  "name": "Erbengemeinschaft nach Josefine Winter (Stefanie Winter und Monica Winter)",
  "naturalPerson": true,
  "squuid": "5be1a6b6-d7b3-4552-871b-6a80fc155afd",
  "controlDate": "2019-05-20T12:10:52.522Z",
  "organizations": [
    {
      "squuid": "5adf79c8-9f9e-4b59-a86f-7119603efa99",
      "name": "DL",
      "type": "organization"
    }
  ],
  "credits": "IJK"
}