{
  "owns": [
    {
      "type": "own",
      "capitalShares": 100.0,
      "held": {
        "name": "Blickpunkt Anzeiger Vertriebs GmbH",
        "squuid": "5ca5f2fe-0298-4106-abbd-287fd3b6becb"
      },
      "squuid": "5ca5f37b-8003-44cf-b0b5-a0d707ba7bae",
      "state": "active"
    }
  ],
  "state": "active",
  "city": "Landshut",
  "pseudoCompany": false,
  "street": "Maybachstr.",
  "name": "Wochenblatt Verlagsgruppe GmbH",
  "naturalPerson": false,
  "squuid": "5be1a6b6-a09e-4fd9-a66f-bccb0bed1d13",
  "controlDate": "2021-12-07T17:23:51.259Z",
  "streetNumber": "8",
  "organizations": [
    {
      "squuid": "5adf79c8-9f9e-4b59-a86f-7119603efa99",
      "name": "DL",
      "type": "organization"
    },
    {
      "squuid": "5adf79c9-1b57-44c7-a29d-9130ab140fa9",
      "name": "GGS",
      "type": "organization",
      "fullName": "Gemeinsame Geschaeftsstelle"
    },
    {
      "squuid": "5b0830ad-2ee5-49b4-b028-a4613bb01c2e",
      "name": "mabb",
      "type": "organization",
      "fullName": "Medienanstalt Berlin-Brandenburg"
    },
    {
      "squuid": "5b0830c1-8ded-40dd-9d37-2a1a21efaff5",
      "name": "BLM",
      "type": "organization",
      "fullName": "Bayerische Landeszentrale für neue Medien"
    },
    {
      "squuid": "5b0830d9-f42f-4d90-b6c6-972961be484a",
      "name": "LMS",
      "type": "organization",
      "fullName": "Landesmedienanstalt Saarland"
    },
    {
      "squuid": "5b0830e0-995b-4e41-bc1e-678fbd483756",
      "name": "LFK",
      "type": "organization",
      "fullName": "Landesanstalt für Kommunikation Baden-Württemberg"
    },
    {
      "squuid": "5b0830ee-abe8-41d3-b591-862c1133d63d",
      "name": "SLM",
      "type": "organization",
      "fullName": "Sächsische Landesanstalt für privaten Rundfunk und neue Medien"
    }
  ],
  "zipcode": "84030",
  "operates": [
    {
      "type": "operate",
      "held": {
        "name": "www.wochenblatt.de",
        "squuid": "5d2c5f8b-8576-4c04-b923-fdd3dc8f3edb"
      },
      "squuid": "5d2c5ff7-256d-42f7-8493-9878e10d2ed2",
      "state": "active"
    }
  ],
  "credits": "BLM-Schriftenreihe Band 83",
  "ownedBy": [
    {
      "type": "own",
      "capitalShares": 100.0,
      "holder": {
        "name": "Optima Vermögensverwaltung GmbH & Co. KG",
        "squuid": "5ca5f336-baa9-467b-bbbc-1fddd912d900"
      },
      "squuid": "5ca5f398-412f-40a4-8348-cbd8e1e3e487",
      "state": "active"
    }
  ]
}