{
  "owns": [
    {
      "type": "own",
      "capitalShares": 5.56,
      "held": {
        "name": "Radio38 GmbH & Co. KG",
        "squuid": "5be1a6b6-f894-439e-aff5-d135b06e6de5"
      },
      "squuid": "5be1a6b8-ec1e-46c5-a575-c4f18bcc1542",
      "state": "active"
    },
    {
      "type": "own",
      "capitalShares": 100.0,
      "held": {
        "name": "Autohaus Wolfsburg Hotz u. Heitmann Geschäftsführungs GmbH",
        "squuid": "5f033c9d-4e92-4c70-b50b-f45155d1e116"
      },
      "squuid": "5f0d897c-02f3-46da-a464-d3337d1f3a4a",
      "state": "active"
    }
  ],
  "state": "active",
  "city": "Wolfsburg",
  "pseudoCompany": false,
  "street": "Heinrich-Nordhoff-Str.",
  "name": "Autohaus Wolfsburg Hotz und Heitmann GmbH & Co. KG",
  "naturalPerson": false,
  "limitedPartnership": true,
  "squuid": "5be1a6b6-0e03-4165-8306-d14c99e558a1",
  "controlDate": "2024-10-04T09:09:10.168Z",
  "streetNumber": "119-123",
  "organizations": [
    {
      "squuid": "5adf79c8-9f9e-4b59-a86f-7119603efa99",
      "name": "DL",
      "type": "organization"
    },
    {
      "squuid": "5b083572-de6f-4f77-b1d0-15f08ed9a01c",
      "name": "NLM",
      "type": "organization",
      "fullName": "Niedersächsische Landesmedienanstalt"
    }
  ],
  "zipcode": "38440",
  "credits": "NLM; Radio38 GmbH & Co. KG",
  "ownedBy": [
    {
      "type": "own",
      "capitalShares": 60.0,
      "holder": {
        "name": "Autohaus Wolfsburg Heitmann GmbH & Co. KG",
        "squuid": "5be1a6b6-f246-40a3-9347-672976bb8967"
      },
      "squuid": "5be1a6b8-12a5-41cb-acc0-bbca1bc8f9c0",
      "state": "active"
    },
    {
      "type": "own",
      "capitalShares": 40.0,
      "holder": {
        "name": "Hotz GmbH & Co. KG",
        "squuid": "5be1a6b6-adcd-4e69-bbad-0e603672dd58"
      },
      "squuid": "5be1a6b8-7458-4106-9e75-25a1bddf33cf",
      "state": "active"
    },
    {
      "complementaryPartner": true,
      "type": "own",
      "capitalShares": 0.0,
      "holder": {
        "name": "Autohaus Wolfsburg Hotz u. Heitmann Geschäftsführungs GmbH",
        "squuid": "5f033c9d-4e92-4c70-b50b-f45155d1e116"
      },
      "squuid": "5f033cd2-2e8c-4484-8b98-83fa02872595",
      "state": "active"
    }
  ]
}