{
  "owns": [
    {
      "type": "own",
      "capitalShares": 2.13,
      "held": {
        "name": "RARI Food International GmbH",
        "squuid": "5d386acb-1942-485a-beb8-f558de2b13d7"
      },
      "squuid": "5d386d70-370e-4194-b965-709e9247810d",
      "state": "active"
    }
  ],
  "state": "active",
  "city": "Langen",
  "pseudoCompany": false,
  "name": "Krefeldt, Uwe",
  "naturalPerson": true,
  "squuid": "5d386d4a-7945-4d89-9675-16ea1885a377",
  "controlDate": "2019-07-24T14:40:35.901Z",
  "organizations": [
    {
      "squuid": "5adf79c8-9f9e-4b59-a86f-7119603efa99",
      "name": "DL",
      "type": "organization"
    }
  ]
}