{
  "owns": [
    {
      "complementaryPartner": true,
      "type": "own",
      "capitalShares": 0.0,
      "held": {
        "name": "Gebrüder Gerstenberg GmbH & Co. KG",
        "squuid": "5be1a6b6-8239-480f-89fa-73f710bd9009"
      },
      "squuid": "5eb2b639-9a4b-4e13-965d-9c52171c2c53",
      "state": "active"
    }
  ],
  "state": "active",
  "city": "Hildesheim",
  "pseudoCompany": false,
  "street": "Rathausstr.",
  "name": "Gebrüder Gerstenberg Geschäftsführungs- und Beteiligungsgesellschaft mbH",
  "naturalPerson": false,
  "squuid": "5eb2b613-ba4e-496b-b0ca-da0fb17c5534",
  "controlDate": "2021-10-25T12:33:33.585Z",
  "streetNumber": "18-20",
  "organizations": [
    {
      "squuid": "5adf79c7-7ca3-4d7a-939c-d5a256934b27",
      "name": "KEK",
      "type": "organization"
    },
    {
      "squuid": "5adf79c8-9f9e-4b59-a86f-7119603efa99",
      "name": "DL",
      "type": "organization"
    },
    {
      "squuid": "5adf79c9-1b57-44c7-a29d-9130ab140fa9",
      "name": "GGS",
      "type": "organization",
      "fullName": "Gemeinsame Geschaeftsstelle"
    },
    {
      "squuid": "5b0830ad-2ee5-49b4-b028-a4613bb01c2e",
      "name": "mabb",
      "type": "organization",
      "fullName": "Medienanstalt Berlin-Brandenburg"
    },
    {
      "squuid": "5b0830d3-6eed-43cd-8b57-958937d68a9f",
      "name": "LPR Hessen",
      "type": "organization",
      "fullName": "Hessische Landesanstalt für privaten Rundfunk und neue Medien"
    },
    {
      "squuid": "5b0830e0-995b-4e41-bc1e-678fbd483756",
      "name": "LFK",
      "type": "organization",
      "fullName": "Landesanstalt für Kommunikation Baden-Württemberg"
    },
    {
      "squuid": "5b0830e6-cba2-4ddc-815e-6454618f2132",
      "name": "brema",
      "type": "organization",
      "fullName": "Bremische Landesmedienanstalt"
    },
    {
      "squuid": "5b0830ee-abe8-41d3-b591-862c1133d63d",
      "name": "SLM",
      "type": "organization",
      "fullName": "Sächsische Landesanstalt für privaten Rundfunk und neue Medien"
    },
    {
      "squuid": "5b0830f6-6588-43fb-93a8-d824a4663969",
      "name": "LfM",
      "type": "organization",
      "fullName": "Landesanstalt für Medien Nordrhein-Westfalen"
    },
    {
      "squuid": "5b0830fd-9e97-4dfd-9136-f2f41022a6c8",
      "name": "MMV",
      "type": "organization",
      "fullName": "Medienanstalt Mecklenburg-Vorpommern"
    },
    {
      "squuid": "5b083104-06da-45cc-a97a-16cb34631424",
      "name": "TLM",
      "type": "organization",
      "fullName": "Thüringer Landesmedienanstalt"
    },
    {
      "squuid": "5b08310a-5980-45c0-b994-009426dae8df",
      "name": "MA HSH",
      "type": "organization",
      "fullName": "Medienanstalt Hamburg/Schleswig-Holstein"
    },
    {
      "squuid": "5b083111-c3f0-4d53-bb60-aa62adaf91b0",
      "name": "MSA",
      "type": "organization",
      "fullName": "Medienanstalt Sachsen-Anhalt"
    },
    {
      "squuid": "5b083572-de6f-4f77-b1d0-15f08ed9a01c",
      "name": "NLM",
      "type": "organization",
      "fullName": "Niedersächsische Landesmedienanstalt"
    }
  ],
  "zipcode": "31134",
  "ownedBy": [
    {
      "type": "own",
      "capitalShares": 70.0,
      "holder": {
        "name": "Gerstenberg, Daniel",
        "squuid": "5be1a6b6-9416-41b7-b5ad-cc8ddc2b417a"
      },
      "squuid": "5f0d8dc3-42b0-49c8-8c8f-2000dcaf3441",
      "state": "active"
    },
    {
      "type": "own",
      "capitalShares": 30.0,
      "holder": {
        "name": "Erbengemeinschaft Dr. Bruno Gerstenberg und Daniel Gerstenberg",
        "squuid": "5f0d8e06-b2fd-481a-a1ed-c62dccd0264b"
      },
      "squuid": "5f0d8e28-9f8f-4e0b-a0b4-31dd7feafbfe",
      "state": "active"
    }
  ]
}