{
  "owns": [
    {
      "complementaryPartner": true,
      "type": "own",
      "capitalShares": 0.0,
      "held": {
        "name": "Dieburger Anzeiger GmbH & Co KG Druck und Verlag",
        "squuid": "5be1a6b6-7afc-4cce-919e-f0a1edf2ab0d"
      },
      "squuid": "5ec3d561-5590-46df-9ad1-aea7dcc0f04d",
      "state": "active"
    }
  ],
  "state": "active",
  "city": "Dieburg",
  "pseudoCompany": false,
  "street": "Mühlgasse ",
  "name": "Dieburger Anzeiger Verwaltungsgesellschaft mbH",
  "naturalPerson": false,
  "squuid": "5ec3d548-fd5f-4963-aa54-e517ccd39240",
  "controlDate": "2023-05-25T12:13:21.531Z",
  "streetNumber": "3",
  "organizations": [
    {
      "squuid": "5adf79c8-9f9e-4b59-a86f-7119603efa99",
      "name": "DL",
      "type": "organization"
    }
  ],
  "zipcode": "64807",
  "ownedBy": [
    {
      "type": "own",
      "capitalShares": 100.0,
      "holder": {
        "name": "Dieburger Anzeiger GmbH & Co KG Druck und Verlag",
        "squuid": "5be1a6b6-7afc-4cce-919e-f0a1edf2ab0d"
      },
      "squuid": "5ec3d5e7-88d4-46f1-8c1e-6fbdfed3da74",
      "state": "active"
    }
  ]
}