{
  "owns": [
    {
      "type": "own",
      "capitalShares": 25.0,
      "held": {
        "name": "Deutsche Vermögensberatung AG ",
        "squuid": "5f02dd72-8c1b-4faa-a1b0-236f43af03f4"
      },
      "squuid": "5f1020e0-585b-4e34-8c25-cb229a06f3b2",
      "state": "active"
    }
  ],
  "state": "active",
  "city": "München",
  "pseudoCompany": false,
  "street": "Adenauerring",
  "name": "Generali Deutschland AG",
  "naturalPerson": false,
  "squuid": "5f102089-b03b-4673-a001-637e4b4bafad",
  "controlDate": "2024-06-06T13:51:41.516Z",
  "streetNumber": "7",
  "organizations": [
    {
      "squuid": "5adf79c7-7ca3-4d7a-939c-d5a256934b27",
      "name": "KEK",
      "type": "organization"
    },
    {
      "squuid": "5adf79c8-9f9e-4b59-a86f-7119603efa99",
      "name": "DL",
      "type": "organization"
    }
  ],
  "zipcode": "81737",
  "ownedBy": [
    {
      "type": "own",
      "capitalShares": 100.0,
      "holder": {
        "name": "Assicurazioni Generali S.p.A.",
        "squuid": "5f155ba1-36d5-4adc-b0ef-cc7a1ad2acfb"
      },
      "squuid": "5f155be8-7f40-46ff-913b-98adfc2fcbe1",
      "state": "active"
    }
  ]
}