{
  "owns": [
    {
      "complementaryPartner": true,
      "type": "own",
      "capitalShares": 0.0,
      "held": {
        "name": "Lokalfunk Remscheid-Solingen Betriebsgesellschaft mbH & Co. KG",
        "squuid": "5be1a6b6-7792-448c-8fae-b97e99f0b6b3"
      },
      "squuid": "5f18110c-5d52-4f17-be2e-3480e1708898",
      "state": "active"
    }
  ],
  "state": "active",
  "city": "Solingen",
  "pseudoCompany": false,
  "street": "Mummstr.",
  "name": "Lokalfunk Remscheid-Solingen Betriebsgesellschaft mbH",
  "naturalPerson": false,
  "squuid": "5f181066-8eaa-43ba-b644-da791aa030f4",
  "controlDate": "2022-07-13T12:43:01.221Z",
  "streetNumber": "9",
  "organizations": [
    {
      "squuid": "5adf79c8-9f9e-4b59-a86f-7119603efa99",
      "name": "DL",
      "type": "organization"
    },
    {
      "squuid": "5b0830f6-6588-43fb-93a8-d824a4663969",
      "name": "LFM NRW",
      "type": "organization",
      "fullName": "Landesanstalt für Medien Nordrhein-Westfalen"
    }
  ],
  "zipcode": "42651",
  "ownedBy": [
    {
      "type": "own",
      "capitalShares": 100.0,
      "holder": {
        "name": "Lokalfunk Remscheid-Solingen Betriebsgesellschaft mbH & Co. KG",
        "squuid": "5be1a6b6-7792-448c-8fae-b97e99f0b6b3"
      },
      "squuid": "609174cf-0ed7-482b-b4df-be79b537ae0f",
      "state": "active"
    }
  ]
}