{
  "owns": [
    {
      "complementaryPartner": true,
      "type": "own",
      "capitalShares": 0.0,
      "held": {
        "name": "Antenne Thüringen GmbH & Co. KG",
        "squuid": "5be1a6b6-5864-4d2d-abd2-19cfbc09b41b"
      },
      "squuid": "5f1e9ac3-d110-46be-bd20-f44b9b693232",
      "state": "active"
    }
  ],
  "state": "active",
  "city": "Weimar",
  "pseudoCompany": false,
  "street": "Schwanseestraße",
  "name": "Antenne Thüringen Verwaltungs-GmbH",
  "naturalPerson": false,
  "squuid": "5f1e961b-d252-417c-b597-1153ee73c985",
  "controlDate": "2023-09-27T10:32:12.015Z",
  "streetNumber": "143",
  "organizations": [
    {
      "squuid": "5adf79c8-9f9e-4b59-a86f-7119603efa99",
      "name": "DL",
      "type": "organization"
    },
    {
      "squuid": "5b083104-06da-45cc-a97a-16cb34631424",
      "name": "TLM",
      "type": "organization",
      "fullName": "Thüringer Landesmedienanstalt"
    }
  ],
  "zipcode": "99427",
  "ownedBy": [
    {
      "type": "own",
      "capitalShares": 100.0,
      "holder": {
        "name": "Antenne Thüringen GmbH & Co. KG",
        "squuid": "5be1a6b6-5864-4d2d-abd2-19cfbc09b41b"
      },
      "squuid": "5fa2bfdf-a8c3-42fe-9d70-be20a86ee3da",
      "state": "active"
    }
  ]
}