{
  "name": "Zerres, Ernst",
  "pseudoCompany": false,
  "squuid": "637ce577-417e-4c46-bf34-ba7d0cd1f779",
  "owns": [
    {
      "type": "own",
      "capitalShares": 1.29,
      "held": {
        "name": "Super Sonntag Verlag GmbH",
        "squuid": "637ce55a-53f5-4df9-aa44-cd1463e88ec5"
      },
      "squuid": "637ce670-4aff-46bb-8083-31e2eb54c5f5",
      "state": "active"
    }
  ],
  "city": "Mönchengladbach",
  "organizations": [
    {
      "squuid": "5adf79c8-9f9e-4b59-a86f-7119603efa99",
      "name": "DL",
      "type": "organization"
    }
  ],
  "state": "active",
  "naturalPerson": true
}