{
  "pressPublishingIntervals": 312,
  "state": "active",
  "rfShoppingChannel": false,
  "pressAsOfDate": "II/21",
  "squuid": "5be1a6b1-fcc6-4056-b145-56e3389c48a1",
  "organization": {
    "squuid": "5adf79c8-9f9e-4b59-a86f-7119603efa99",
    "name": "DL",
    "type": "organization"
  },
  "rfStatewide": false,
  "operatedBy": [
    {
      "type": "operate",
      "holder": {
        "name": "Medienhaus Aachen GmbH",
        "squuid": "5be1a6b6-0200-4a40-921b-ce08c00a32ac"
      },
      "squuid": "5be1a6b9-e444-496b-b6cd-5fb3dc2c5bb1",
      "state": "active"
    }
  ],
  "name": "Heinsberger Zeitung",
  "pressEditionsIVW": true,
  "pressDistributionArea": "Lk Heinsberg",
  "type": "print",
  "pressEditionsEpaper": 1315,
  "controlDate": "2021-10-25T11:04:12.778Z",
  "onlineOfferType": {
    "squuid": "5be1a6b0-e359-4db0-9c54-8ab7d725db5e",
    "name": "Online Medienangebot",
    "type": "online-offer-type",
    "state": "active"
  },
  "pressEditionsComments": "inkl. Heinsberger Nachrichten und Geilenkirchener Zeitung",
  "pressEditionsSold": 13088,
  "pressType": {
    "squuid": "5be1a6b0-e4cc-4064-9625-597855abfd7c",
    "name": "Zeitung",
    "type": "press-type",
    "state": "active"
  }
}