{
  "pressPublishingIntervals": 312,
  "state": "active",
  "rfShoppingChannel": false,
  "pressAsOfDate": "I/23",
  "squuid": "5be1a6b1-2be4-41d3-9636-22c053b22933",
  "organization": {
    "squuid": "5adf79c8-9f9e-4b59-a86f-7119603efa99",
    "name": "DL",
    "type": "organization"
  },
  "rfStatewide": false,
  "operatedBy": [
    {
      "type": "operate",
      "holder": {
        "name": "Bremer Tageszeitungen AG",
        "squuid": "5be1a6b6-d195-4cf4-a6a4-906cfae4b85f"
      },
      "squuid": "5be1a6b9-113e-4f4a-a7d6-f5192c851fc7",
      "state": "active"
    }
  ],
  "name": "Bremer Nachrichten",
  "pressEditionsIVW": true,
  "pressDistributionArea": "kreisfreie Stadt Bremen, kreisfreie Stadt Delmenhorst, Lk Oldenburg, Lk Wesermarsch, Lk Osterholz, Lk Verden, Lk Diepholz",
  "type": "print",
  "controlDate": "2023-12-06T11:35:51.676Z",
  "onlineOfferType": {
    "squuid": "5be1a6b0-e359-4db0-9c54-8ab7d725db5e",
    "name": "Online Medienangebot",
    "type": "online-offer-type",
    "state": "active"
  },
  "pressEditionsComments": "siehe unter Weser Kurier",
  "pressType": {
    "squuid": "5be1a6b0-e4cc-4064-9625-597855abfd7c",
    "name": "Zeitung",
    "type": "press-type",
    "state": "active"
  }
}