{
  "pressPublishingIntervals": 6,
  "state": "active",
  "rfShoppingChannel": false,
  "pressMagazineType": {
    "squuid": "5be1a6b0-bff8-40db-a254-72d8fa6d3386",
    "name": "Publikumszeitschrift",
    "type": "press-magazine-type",
    "state": "active"
  },
  "pressAsOfDate": "I/24",
  "squuid": "5be1a6b1-66f3-44c4-bd72-5259f5ec8b5f",
  "organization": {
    "squuid": "5adf79c8-9f9e-4b59-a86f-7119603efa99",
    "name": "DL",
    "type": "organization"
  },
  "rfStatewide": false,
  "operatedBy": [
    {
      "type": "operate",
      "holder": {
        "name": "BLOOM's GmbH Medien Marketing Events",
        "squuid": "5be1a6b6-7132-4bc4-bf43-24dfc9a78307"
      },
      "squuid": "5be1a6b9-3d99-420a-9bd2-78d30563ba32",
      "state": "active"
    }
  ],
  "name": "BLOOM's Deco",
  "pressEditionsIVW": true,
  "pressDistributionArea": "bundesweit",
  "type": "print",
  "controlDate": "2024-05-17T12:35:30.248Z",
  "pressKind": "Wohnen",
  "onlineOfferType": {
    "squuid": "5be1a6b0-e359-4db0-9c54-8ab7d725db5e",
    "name": "Online Medienangebot",
    "type": "online-offer-type",
    "state": "active"
  },
  "pressEditionsSold": 16263,
  "pressType": {
    "squuid": "5be1a6b0-8202-4312-8190-cd96a1973f23",
    "name": "Zeitschrift",
    "type": "press-type",
    "state": "active"
  }
}