{
  "pressPublishingIntervals": 12,
  "state": "active",
  "rfShoppingChannel": false,
  "pressMagazineType": {
    "squuid": "5be1a6b0-bff8-40db-a254-72d8fa6d3386",
    "name": "Publikumszeitschrift",
    "type": "press-magazine-type",
    "state": "active"
  },
  "pressAsOfDate": "",
  "squuid": "5be1a6b1-fca5-4984-89ba-4770052ed2a7",
  "organization": {
    "squuid": "5adf79c8-9f9e-4b59-a86f-7119603efa99",
    "name": "DL",
    "type": "organization"
  },
  "rfStatewide": false,
  "operatedBy": [
    {
      "type": "operate",
      "holder": {
        "name": "Rock Hard Verlags- und Handelsgesellschaft mbH",
        "squuid": "5be1a6b6-6eca-4e7a-bbbf-cc539e3ec75a"
      },
      "squuid": "5be1a6b9-3f31-4629-af94-ae0ed7cb112b",
      "state": "active"
    }
  ],
  "name": "Rock Hard",
  "pressEditionsIVW": false,
  "pressDistributionArea": "bundesweit",
  "type": "print",
  "controlDate": "2025-12-11T15:36:03.592Z",
  "pressKind": "Lifestyle",
  "onlineOfferType": {
    "squuid": "5be1a6b0-e359-4db0-9c54-8ab7d725db5e",
    "name": "Online Medienangebot",
    "type": "online-offer-type",
    "state": "active"
  },
  "pressEditionsSold": 20000,
  "pressType": {
    "squuid": "5be1a6b0-8202-4312-8190-cd96a1973f23",
    "name": "Zeitschrift",
    "type": "press-type",
    "state": "active"
  }
}