{
  "state": "active",
  "onlineAsOfDateIVW": "3/24",
  "rfShoppingChannel": false,
  "squuid": "5be1a6b1-a97b-42b0-b89d-5e8b4a0c9c2a",
  "organization": {
    "squuid": "5adf79c8-9f9e-4b59-a86f-7119603efa99",
    "name": "DL",
    "type": "organization"
  },
  "operatedBy": [
    {
      "type": "operate",
      "holder": {
        "name": "Delius Klasing Verlag GmbH",
        "squuid": "5bf5632e-84b8-4e00-aa9b-1bc829792215"
      },
      "squuid": "6331a1e4-7d14-4d9f-abe8-ae39f413d961",
      "state": "active"
    }
  ],
  "name": "www.tour-magazin.de",
  "pressEditionsIVW": false,
  "type": "online",
  "controlDate": "2024-05-24T15:00:24.161Z",
  "onlineIVWPI": 2311700,
  "onlineAsOfDateAGOF": "",
  "onlineOfferType": {
    "squuid": "5be1a6b0-e359-4db0-9c54-8ab7d725db5e",
    "name": "Online Medienangebot",
    "type": "online-offer-type",
    "state": "active"
  },
  "onlineVisitsIVW": 744300,
  "onlineAGOF": 0
}