{
  "state": "active",
  "onlineAsOfDateIVW": "",
  "rfShoppingChannel": false,
  "squuid": "5be1a6b1-760e-4a8f-96ca-341350210c41",
  "organization": {
    "squuid": "5adf79c8-9f9e-4b59-a86f-7119603efa99",
    "name": "DL",
    "type": "organization"
  },
  "operatedBy": [
    {
      "type": "operate",
      "holder": {
        "name": "The Walt Disney Company Ltd.",
        "squuid": "60d5c979-e693-4dae-81ab-d4dde7c983dd"
      },
      "squuid": "62cbff6a-ba04-4d4e-8043-eb676b351ea6",
      "state": "active"
    }
  ],
  "name": "www.nationalgeographic.de",
  "pressEditionsIVW": false,
  "type": "online",
  "controlDate": "2026-01-26T09:46:50.740Z",
  "onlineIVWPI": 0,
  "onlineAsOfDateAGOF": "",
  "onlineOfferType": {
    "squuid": "5be1a6b0-e359-4db0-9c54-8ab7d725db5e",
    "name": "Online Medienangebot",
    "type": "online-offer-type",
    "state": "active"
  },
  "onlineVisitsIVW": 0,
  "onlineAGOF": 0
}