{
  "state": "active",
  "onlineAsOfDateIVW": "11/24",
  "squuid": "5c51a868-a04d-4a48-a03a-13f8944d0282",
  "organization": {
    "squuid": "5adf79c8-9f9e-4b59-a86f-7119603efa99",
    "name": "DL",
    "type": "organization"
  },
  "operatedBy": [
    {
      "type": "operate",
      "holder": {
        "name": "Audiotainment Südwest GmbH & Co. KG",
        "squuid": "6023df17-5ffb-4374-a0dd-4013ac8b5f6f"
      },
      "squuid": "64649c3a-4cbb-4d15-ba9a-4f0e3b71c924",
      "state": "active"
    }
  ],
  "name": "www.bigfm.de",
  "rfPublicPrivate": false,
  "type": "online",
  "controlDate": "2025-09-16T11:38:10.981Z",
  "onlineIVWPI": 1584600,
  "onlineAsOfDateAGOF": "",
  "rfSupervisingAuthority": {
    "squuid": "5adf79c8-9f9e-4b59-a86f-7119603efa99",
    "name": "DL",
    "type": "organization"
  },
  "onlineOfferType": {
    "squuid": "5be1a6b0-e359-4db0-9c54-8ab7d725db5e",
    "name": "Online Medienangebot",
    "type": "online-offer-type",
    "state": "active"
  },
  "onlineVisitsIVW": 638000,
  "onlineAGOF": 0
}