{
  "pressPublishingIntervals": 12,
  "state": "active",
  "pressMagazineType": {
    "squuid": "5be1a6b0-bff8-40db-a254-72d8fa6d3386",
    "name": "Publikumszeitschrift",
    "type": "press-magazine-type",
    "state": "active"
  },
  "pressAsOfDate": "III/23",
  "squuid": "5d0b50da-3d86-4031-a370-bf3950008ed3",
  "organization": {
    "squuid": "5adf79c8-9f9e-4b59-a86f-7119603efa99",
    "name": "DL",
    "type": "organization"
  },
  "operatedBy": [
    {
      "type": "operate",
      "holder": {
        "name": "Peregrinus GmbH",
        "squuid": "5be1a6b6-83a2-4e8a-a5a1-af7126f553cd"
      },
      "squuid": "5df21f4b-8709-4498-86a1-6f0dfd862bba",
      "state": "active"
    }
  ],
  "name": "der pilger - Magazin für bewusstes Leben",
  "pressEditionsIVW": true,
  "rfPublicPrivate": false,
  "pressDistributionArea": "Bistum Speyer",
  "type": "print",
  "controlDate": "2023-12-07T13:50:56.796Z",
  "rfSupervisingAuthority": {
    "squuid": "5adf79c8-9f9e-4b59-a86f-7119603efa99",
    "name": "DL",
    "type": "organization"
  },
  "pressKind": "Konfession",
  "pressEditionsSold": 8706,
  "pressType": {
    "squuid": "5be1a6b0-8202-4312-8190-cd96a1973f23",
    "name": "Zeitschrift",
    "type": "press-type",
    "state": "active"
  }
}