{
  "rfRepresentative": "Harald Gehrung",
  "state": "active",
  "squuid": "5e1735a1-14bd-42ac-9b65-9096628f3665",
  "organization": {
    "squuid": "5b0830e6-cba2-4ddc-815e-6454618f2132",
    "name": "brema",
    "type": "organization",
    "fullName": "Bremische Landesmedienanstalt"
  },
  "accessibilityUrl": "https://www.radioroland.de/",
  "rfStatewide": true,
  "operatedBy": [
    {
      "type": "operate",
      "holder": {
        "name": "Funk & Fernsehen Nordwestdeutschland GmbH & Co. KG",
        "squuid": "5be1a6b6-6d31-40f9-81d9-39e930c9b6cb"
      },
      "squuid": "5e173652-0dfa-43a6-8e02-8c616fadbe57",
      "state": "active"
    }
  ],
  "name": "Radio Roland (Bundesweit)",
  "rfPublicPrivate": false,
  "type": "radio",
  "rfSupervisingAuthority": {
    "squuid": "5b0830e6-cba2-4ddc-815e-6454618f2132",
    "name": "brema",
    "type": "organization",
    "fullName": "Bremische Landesmedienanstalt"
  },
  "rfLicenseUntil": "16. Februar 2028",
  "rfLicensed": "15. Februar 2018",
  "rfLicenseFrom": "16. Februar 2018",
  "accessibilityEmail": "radio@radioroland.de"
}