{
  "pressPublishingIntervals": 52,
  "state": "active",
  "pressAsOfDate": "",
  "squuid": "63f741d8-3f29-4beb-8a83-3c43bf722e1d",
  "organization": {
    "squuid": "5adf79c8-9f9e-4b59-a86f-7119603efa99",
    "name": "DL",
    "type": "organization"
  },
  "operatedBy": [
    {
      "type": "operate",
      "holder": {
        "name": "RND RedaktionsNetzwerk Deutschland GmbH",
        "squuid": "5be1a6b6-e0ae-4887-b782-279cfa1f411d"
      },
      "squuid": "63f74209-5662-4f5e-a1a1-592e78535fd3",
      "state": "active"
    },
    {
      "type": "operate",
      "holder": {
        "name": "Märkische Verlags- und Druck-Gesellschaft mbH Potsdam",
        "squuid": "5be1a6b6-8cd1-46d4-85d9-5e8bbee063fe"
      },
      "squuid": "65ca5386-7a30-4a0a-8481-f27fb2be03f5",
      "state": "active"
    }
  ],
  "name": "MAZ am Sonntag",
  "pressEditionsIVW": false,
  "rfPublicPrivate": false,
  "pressDistributionArea": "nur als ePaper",
  "type": "print",
  "controlDate": "2025-12-02T11:36:02.615Z",
  "rfSupervisingAuthority": {
    "squuid": "5adf79c8-9f9e-4b59-a86f-7119603efa99",
    "name": "DL",
    "type": "organization"
  },
  "pressType": {
    "squuid": "5be1a6b0-4e68-459d-a5ee-da3974114c2a",
    "name": "E-Paper",
    "type": "press-type",
    "state": "active"
  }
}